[{"amount":150,"days_to_due":0,"category":"Services","project_status":"PENDING"},{"amount":100,"days_to_due":0,"category":"nnnnnn","project_status":"PENDING"},{"amount":200,"days_to_due":0,"category":"aaaaa","project_status":"PENDING"},{"amount":200,"days_to_due":0,"category":"aaaaa","project_status":"PENDING"},{"amount":200,"days_to_due":0,"category":"aaaaa","project_status":"PENDING"},{"amount":200,"days_to_due":0,"category":"aaaaa","project_status":"PENDING"},{"amount":200,"days_to_due":0,"category":"N/A","project_status":"PENDING"},{"amount":300,"days_to_due":0,"category":"tag","project_status":"PENDING"},{"amount":200,"days_to_due":0,"category":"aaaaa","project_status":"PENDING"},{"amount":99.99,"days_to_due":0,"category":"aa","project_status":"PENDING"},{"amount":100,"days_to_due":0,"category":"Services","project_status":"PENDING"},{"amount":199.84,"days_to_due":0,"category":"Services","project_status":"PENDING"},{"amount":100,"days_to_due":0,"category":"Freelance","project_status":"PENDING"},{"amount":5,"days_to_due":0,"category":"Products","project_status":"PENDING"},{"amount":50,"days_to_due":0,"category":"Services","project_status":"PENDING"},{"amount":100,"days_to_due":11,"category":"Maintenance","project_status":"PENDING"}]